[
  {
    "code": "MYBA092",
    "title": "人妻の花びらめくり 涼菜波美",
    "size": "4.4 GB",
    "image_url": "https://pics.dmm.co.jp/mono/movie/adult/myba092/myba092pl.jpg",
    "torrent_url": "https://onejav.com/torrent/myba092/download/60055229/onejav.com_myba092.torrent",
    "tags": "Affair, Breasts, Creampie, Married Woman, Mature Woman, Solowork",
    "actresses": "涼菜波美",
    "date": "2026-03-14",
    "page_url": "https://onejav.com/torrent/myba092"
  },
  {
    "code": "JUR603",
    "title": "義父と同居して4年…これは私が生で挿入され続けて、快感に目覚めて、妊娠するまでの話です。 涼菜波美",
    "size": "6.7 GB",
    "image_url": "https://pics.dmm.co.jp/mono/movie/adult/jur603/jur603pl.jpg",
    "torrent_url": "https://onejav.com/torrent/jur603/download/84525002/onejav.com_jur603.torrent",
    "tags": "Breasts, Creampie, Cuckold, Married Woman, Mature Woman, Solowork",
    "actresses": "涼菜波美",
    "date": "2026-01-23",
    "page_url": "https://onejav.com/torrent/jur603"
  },
  {
    "code": "JUR561",
    "title": "眠れない森の美人妻 マドンナ専属 第2弾！！ 中出し解禁！！ 夫の親友に孕ませられた私 涼菜波美",
    "size": "4.8 GB",
    "image_url": "https://pics.dmm.co.jp/mono/movie/adult/jur561/jur561pl.jpg",
    "torrent_url": "https://onejav.com/torrent/jur561/download/17231193/onejav.com_jur561.torrent",
    "tags": "Breasts, Creampie, Cuckold, Married Woman, Mature Woman, Solowork",
    "actresses": "涼菜波美",
    "date": "2025-12-19",
    "page_url": "https://onejav.com/torrent/jur561"
  },
  {
    "code": "JUR054",
    "title": "眠れない森の美人妻 涼菜波美 28歳 AV DEBUT",
    "size": "5.2 GB",
    "image_url": "https://pics.dmm.co.jp/mono/movie/adult/jur054/jur054pl.jpg",
    "torrent_url": "https://onejav.com/torrent/jur054/download/23935204/onejav.com_jur054.torrent",
    "tags": "Affair, Breasts, Debut Production, Married Woman, Mature Woman, Solowork",
    "actresses": "涼菜波美",
    "date": "2025-11-21",
    "page_url": "https://onejav.com/torrent/jur054"
  }
]