[
  {
    "code": "EBWH315",
    "title": "「タバコ吸わずにおっぱい吸えば？」 喫煙やめなきゃ命危ない僕を心配して… いつでもどこでも乳差し出してくる 禁煙おっパ×ポ彼女 莉々はるか",
    "size": "4.9 GB",
    "image_url": "https://pics.dmm.co.jp/mono/movie/adult/ebwh315/ebwh315pl.jpg",
    "torrent_url": "https://onejav.com/torrent/ebwh315/download/38437862/onejav.com_ebwh315.torrent",
    "tags": "Acme · Orgasm, Big Tits, Blow, Busty Fetish, Solowork, Titty Fuck",
    "actresses": "莉々はるか",
    "date": "2026-03-13",
    "page_url": "https://onejav.com/torrent/ebwh315"
  },
  {
    "code": "NTRH020",
    "title": "うちの巨乳ツレが変態上司に乳ワイパー性交で辱められまして。 莉々はるか",
    "size": "6.6 GB",
    "image_url": "https://pics.dmm.co.jp/mono/movie/adult/ntrh020/ntrh020pl.jpg",
    "torrent_url": "https://onejav.com/torrent/ntrh020/download/54879461/onejav.com_ntrh020.torrent",
    "tags": "Acme · Orgasm, Big Tits, Busty Fetish, Cuckold, OL, Solowork",
    "actresses": "莉々はるか",
    "date": "2025-12-26",
    "page_url": "https://onejav.com/torrent/ntrh020"
  },
  {
    "code": "EBWH274",
    "title": "カラミ酒誘惑してくる隣家のだらしな巨乳ネキ 莉々はるか",
    "size": "5.6 GB",
    "image_url": "https://pics.dmm.co.jp/mono/movie/adult/ebwh274/ebwh274pl.jpg",
    "torrent_url": "https://onejav.com/torrent/ebwh274/download/06911352/onejav.com_ebwh274.torrent",
    "tags": "Big Tits, Blow, Busty Fetish, Older Sister, Solowork, Titty Fuck",
    "actresses": "莉々はるか",
    "date": "2025-11-14",
    "page_url": "https://onejav.com/torrent/ebwh274"
  },
  {
    "code": "CKCK020",
    "title": "性欲まみれの思春期生徒たちにぶっ刺さる！ 豊満Hcup水泳部顧問のドエロい競泳水着と性教育的指導 莉々はるか",
    "size": "6.1 GB",
    "image_url": "https://pics.dmm.co.jp/mono/movie/adult/ckck020/ckck020pl.jpg",
    "torrent_url": "https://onejav.com/torrent/ckck020/download/20345176/onejav.com_ckck020.torrent",
    "tags": "Creampie, Female Teacher, School Swimsuit, Slut, Solowork, Titty Fuck",
    "actresses": "莉々はるか",
    "date": "2025-09-26",
    "page_url": "https://onejav.com/torrent/ckck020"
  },
  {
    "code": "MIMK204",
    "title": "-実写版- 巨乳の友達と付き合うまでの話 前編 莉々はるか",
    "size": "5.0 GB",
    "image_url": "https://pics.dmm.co.jp/mono/movie/adult/mimk204/mimk204pl.jpg",
    "torrent_url": "https://onejav.com/torrent/mimk204/download/40922333/onejav.com_mimk204.torrent",
    "tags": "Big Tits, Original Collaboration, Solowork, Titty Fuck, Ultra-Huge Tits, Uniform",
    "actresses": "莉々はるか",
    "date": "2025-03-28",
    "page_url": "https://onejav.com/torrent/mimk204"
  },
  {
    "code": "EBWH208",
    "title": "僕がずっと前から好きだった真面目な文学系幼馴染は、嫌いなヤリチン先輩に染められ、調教され、寝取られ堕ちた。 莉々はるか",
    "size": "5.2 GB",
    "image_url": "https://pics.dmm.co.jp/mono/movie/adult/ebwh208/ebwh208pl.jpg",
    "torrent_url": "https://onejav.com/torrent/ebwh208/download/41348378/onejav.com_ebwh208.torrent",
    "tags": "Beautiful Girl, Big Tits, Cuckold, Nasty, Hardcore, Solowork",
    "actresses": "莉々はるか",
    "date": "2025-03-19",
    "page_url": "https://onejav.com/torrent/ebwh208"
  },
  {
    "code": "EBWH184",
    "title": "「ザコなカテキョのくせに中出しする度胸だけはあるんですね」 大人を色仕掛けでバカにしてくる文学系爆乳マセガキに負かされたい… 莉々はるか",
    "size": "5.2 GB",
    "image_url": "https://pics.dmm.co.jp/mono/movie/adult/ebwh184/ebwh184pl.jpg",
    "torrent_url": "https://onejav.com/torrent/ebwh184/download/68160560/onejav.com_ebwh184.torrent",
    "tags": "Creampie, M男, Solowork, Titty Fuck, Tutor",
    "actresses": "莉々はるか",
    "date": "2024-12-13",
    "page_url": "https://onejav.com/torrent/ebwh184"
  },
  {
    "code": "EBWH157",
    "title": "7種のおっぱい強調コスプレと チ○ポ馬鹿になるほど気持ち良いパイズリ挟射 莉々はるか",
    "size": "6.4 GB",
    "image_url": "https://pics.dmm.co.jp/mono/movie/adult/ebwh157/ebwh157pl.jpg",
    "torrent_url": "https://onejav.com/torrent/ebwh157/download/28382064/onejav.com_ebwh157.torrent",
    "tags": "Big Tits, Bunny Girl, Busty Fetish, Cosplay, Solowork, Titty Fuck",
    "actresses": "莉々はるか",
    "date": "2024-10-11",
    "page_url": "https://onejav.com/torrent/ebwh157"
  },
  {
    "code": "EBWH148",
    "title": "街で見かけたら鷲掴みしたくなる 犯罪的着衣巨乳ちゃんの誘惑 僕らの夢を叶えるスケベ妄想4シチュエーション 莉々はるか",
    "size": "6.7 GB",
    "image_url": "https://pics.dmm.co.jp/mono/movie/adult/ebwh148/ebwh148pl.jpg",
    "torrent_url": "https://onejav.com/torrent/ebwh148/download/28214020/onejav.com_ebwh148.torrent",
    "tags": "Big Tits, Busty Fetish, Other Fetish, Slut, Solowork, Titty Fuck",
    "actresses": "莉々はるか",
    "date": "2024-09-13",
    "page_url": "https://onejav.com/torrent/ebwh148"
  },
  {
    "code": "EBWH138",
    "title": "地味眼鏡OLだけど…巨乳でスケベで痴女だったら興奮してくれますか？ 莉々はるか",
    "size": "5.2 GB",
    "image_url": "https://pics.dmm.co.jp/mono/movie/adult/ebwh138/ebwh138pl.jpg",
    "torrent_url": "https://onejav.com/torrent/ebwh138/download/29168070/onejav.com_ebwh138.torrent",
    "tags": "Big Tits, Blow, Nasty, Hardcore, Slut, Solowork, Titty Fuck",
    "actresses": "莉々はるか",
    "date": "2024-08-16",
    "page_url": "https://onejav.com/torrent/ebwh138"
  }
]