[
  {
    "code": "FC2PPV4843590",
    "title": "FC2-PPV-4843590 【完全素人】人妻･音楽教師(29歳･Gカップ)をNTR。スレンダー爆乳な美体が他人棒でヒクヒクとイキまくる背徳不倫記録。",
    "size": "776.6 MB",
    "image_url": "https://contents-thumbnail2.fc2.com/w1280/storage201000.contents.fc2.com/file/387/38679946/1770271304.37.jpg",
    "torrent_url": "https://onejav.com/torrent/fc2ppv4843590/download/65138409/onejav.com_fc2ppv4843590.torrent",
    "tags": "Affair, Amateur, Beautiful Girl, Big Tits, Blow, FC2, Female Teacher, Married Woman, POV, Titty Fuck",
    "actresses": "",
    "date": "2026-02-07",
    "page_url": "https://onejav.com/torrent/fc2ppv4843590"
  },
  {
    "code": "SIRO5615",
    "title": "可愛すぎて即勃起！経験人数少なめなぎこちないセックスがなんかいい。。。【りりか 20歳 学生】 押し返すくらいギュンギュンに締め付ける膣に容赦なくねじ込むパワーセックス！！ 若いマ●コはたまんない。。。 【初撮り】ネットでAV応募→AV体験撮影 2504",
    "size": "2.4 GB",
    "image_url": "https://image.mgstage.com/images/shirouto/siro/5615/pb_e_siro-5615.jpg",
    "torrent_url": "https://onejav.com/torrent/siro5615/download/58752105/onejav.com_siro5615.torrent",
    "tags": "Amateur, Beautiful Girl, Big Tits, Butt, Debut Production, POV",
    "actresses": "",
    "date": "2026-02-07",
    "page_url": "https://onejav.com/torrent/siro5615"
  },
  {
    "code": "FC2PPV4844878",
    "title": "FC2-PPV-4844878 【27迄1090pt】【初撮】【潮吹】Hカップ色白の天然美巨乳ムスメ。「あぁ...イク...！」巨根に豊満ボディーをしっかり教育され、　喘ぎながら何度も痙攣。ピクピクして感度抜群な敏感マンコに中出し。",
    "size": "4.3 GB",
    "image_url": "https://contents-thumbnail2.fc2.com/w1280/storage201000.contents.fc2.com/file/370/36940995/1770342909.51.png",
    "torrent_url": "https://onejav.com/torrent/fc2ppv4844878/download/02442862/onejav.com_fc2ppv4844878.torrent",
    "tags": "Amateur, Big Tits, Blow, Breasts, Creampie, FC2, Uncensored",
    "actresses": "",
    "date": "2026-02-07",
    "page_url": "https://onejav.com/torrent/fc2ppv4844878"
  },
  {
    "code": "FC2PPV4843524",
    "title": "FC2-PPV-4843524 [期間限定で大放出!15000pt➡1980pt]無修正＜元野球部マネージャー♡AFTERclass＞初々しさ満載制服スレンダースタイルが震える痙攣絶頂！途中ゴム外⇒***生ピストンで受精必至の中出し",
    "size": "5.6 GB",
    "image_url": "https://contents-thumbnail2.fc2.com/w1280/storage200000.contents.fc2.com/file/373/37232976/1770264319.49.jpg",
    "torrent_url": "https://onejav.com/torrent/fc2ppv4843524/download/26520357/onejav.com_fc2ppv4843524.torrent",
    "tags": "Amateur, Blow, Breasts, Creampie, FC2, Long Hair, Nasty, Hardcore, POV, Shaved, Uncensored, Uniform",
    "actresses": "",
    "date": "2026-02-07",
    "page_url": "https://onejav.com/torrent/fc2ppv4843524"
  },
  {
    "code": "MKMP706",
    "title": "",
    "size": "5.0 GB",
    "image_url": "https://pics.dmm.co.jp/mono/movie/adult/mkmp706/mkmp706pl.jpg",
    "torrent_url": "https://onejav.com/torrent/mkmp706/download/44001509/onejav.com_mkmp706.torrent",
    "tags": "",
    "actresses": "",
    "date": "2026-02-07",
    "page_url": "https://onejav.com/torrent/mkmp706"
  },
  {
    "code": "MADM215",
    "title": "その唇と乳房と美尻に釘付け…人妻不倫デート 旦那とはセックスレスな美人妻と一日中何度もたっぷり中出し性交。ゆいか 28歳 小野坂ゆいか",
    "size": "5.8 GB",
    "image_url": "https://pics.dmm.co.jp/mono/movie/adult/madm215/madm215pl.jpg",
    "torrent_url": "https://onejav.com/torrent/madm215/download/53094358/onejav.com_madm215.torrent",
    "tags": "Affair, Big Tits, Butt, Date, Facials, Huge Cock, Married Woman, Masturbation, Shaved, Solowork, Squirting",
    "actresses": "小野坂ゆいか",
    "date": "2026-02-07",
    "page_url": "https://onejav.com/torrent/madm215"
  },
  {
    "code": "DVAJ730",
    "title": "アクメ寸前マ○コを低速こねくりピストンで焦らしてから爆速ピストンラッシュでアクメギリギリに追い込む変速ギアチェンジ責めで完堕ちした美人妻のアへ顔トロ顔オホ顔ンホ面イッちゃってる顔面特化アングル 森沢かな",
    "size": "5.3 GB",
    "image_url": "https://pics.dmm.co.jp/mono/movie/adult/dvaj730/dvaj730pl.jpg",
    "torrent_url": "https://onejav.com/torrent/dvaj730/download/00942766/onejav.com_dvaj730.torrent",
    "tags": "Acme · Orgasm, Affair, Creampie, Cuckold, Deep Throating, Drug, Married Woman, Nasty, Hardcore, Solowork, Squirting",
    "actresses": "飯岡かなこ",
    "date": "2026-02-07",
    "page_url": "https://onejav.com/torrent/dvaj730"
  },
  {
    "code": "FC2PPV4843473",
    "title": "FC2-PPV-4843473 【無】元チアの体感が強烈なスパイダー騎乗位！チ〇コの先っちょから根本までしっかり締め上げる⤴初顔射に中だし！※特典高画質",
    "size": "3.7 GB",
    "image_url": "https://contents-thumbnail2.fc2.com/w1280/storage200000.contents.fc2.com/file/381/38003297/1770258339.73.jpg",
    "torrent_url": "https://onejav.com/torrent/fc2ppv4843473/download/31159525/onejav.com_fc2ppv4843473.torrent",
    "tags": "Amateur, Beautiful Girl, Big Tits, Blow, Creampie, FC2, POV, Uncensored",
    "actresses": "",
    "date": "2026-02-07",
    "page_url": "https://onejav.com/torrent/fc2ppv4843473"
  },
  {
    "code": "DVAJ727",
    "title": "時間停止男に動かぬカラダを毎日イジくり回され知らぬ間に感度ビンビン 解除後に全身を駆け巡る350倍の蓄積快楽でアクメ堕ち寸前の潮吹きザコマ○コは追いピスされても生中出しを拒否できない 天馬ゆい",
    "size": "4.7 GB",
    "image_url": "https://pics.dmm.co.jp/mono/movie/adult/dvaj727/dvaj727pl.jpg",
    "torrent_url": "https://onejav.com/torrent/dvaj727/download/12676286/onejav.com_dvaj727.torrent",
    "tags": "Acme · Orgasm, Creampie, Cuckold, Deep Throating, Drug, Nasty, Hardcore, OL, Solowork, Squirting, Time Stop",
    "actresses": "天馬ゆい",
    "date": "2026-02-07",
    "page_url": "https://onejav.com/torrent/dvaj727"
  },
  {
    "code": "FC2PPV4844839",
    "title": "FC2-PPV-4844839 《2/13まで1980pt》【無】一線を踏み越えた神ボディラインの圧倒的巨乳美女！！ 美マンで美アヌス♪ 種活に夢中のスレンダークビレFカップに大量種付け！！",
    "size": "2.9 GB",
    "image_url": "https://contents-thumbnail2.fc2.com/w1280/storage201000.contents.fc2.com/file/387/38616959/1770339007.57.JPG",
    "torrent_url": "https://onejav.com/torrent/fc2ppv4844839/download/57867786/onejav.com_fc2ppv4844839.torrent",
    "tags": "Amateur, Big Tits, Butt, Creampie, FC2, POV, Slender, Uncensored",
    "actresses": "",
    "date": "2026-02-07",
    "page_url": "https://onejav.com/torrent/fc2ppv4844839"
  }
]