[
  {
    "code": "FC2PPV4862424",
    "title": "FC2-PPV-4862424 【7日間限定75％OFF】極上美肌のギャルエステ、生フェラ、生出しで猛興奮！綺麗な体をたっぷりたんのうしちゃいました。 【無修正・中出し】",
    "size": "4.0 GB",
    "image_url": "https://contents-thumbnail2.fc2.com/w1280/storage201000.contents.fc2.com/file/381/38031442/1773235298.84.png",
    "torrent_url": "https://onejav.com/torrent/fc2ppv4862424/download/66741456/onejav.com_fc2ppv4862424.torrent",
    "tags": "Amateur, Beautiful Girl, Blow, Breasts, Butt, Creampie, FC2, Gal, Uncensored",
    "actresses": "",
    "date": "2026-05-23",
    "page_url": "https://onejav.com/torrent/fc2ppv4862424"
  },
  {
    "code": "FC2PPV4904351",
    "title": "FC2-PPV-4904351 50％OFF【初撮り】ナースちゃん、夜の看護は大忙し！？色白パイパンのカラダを大開発！！潮吹きからのハメ潮で大量潮吹き！！！止まらぬ潮吹きに大興奮！野外で中出し、ベットで中出しで大満足！最後はガシマン",
    "size": "4.3 GB",
    "image_url": "https://contents-thumbnail2.fc2.com/w1280/storage201000.contents.fc2.com/file/385/38454154/1779295232.15.jpg",
    "torrent_url": "https://onejav.com/torrent/fc2ppv4904351/download/67246334/onejav.com_fc2ppv4904351.torrent",
    "tags": "Amateur, Breasts, Butt, Creampie, Debut Production, FC2, POV, Shaved, Squirting, Uncensored",
    "actresses": "",
    "date": "2026-05-23",
    "page_url": "https://onejav.com/torrent/fc2ppv4904351"
  },
  {
    "code": "FC2PPV4903955",
    "title": "FC2-PPV-4903955 【無】超ノリが良い長身171㎝スタイル抜群Ｇカップ美尻美女降臨！上品な顔してエゲツナイすけべ⤴唾液垂らしまくりのフェラに素晴らしいパイズリで射精と中だし！※特典高画質",
    "size": "4.3 GB",
    "image_url": "https://contents-thumbnail2.fc2.com/w1280/storage200000.contents.fc2.com/file/381/38003297/1779234774.02.jpg",
    "torrent_url": "https://onejav.com/torrent/fc2ppv4903955/download/50553770/onejav.com_fc2ppv4903955.torrent",
    "tags": "Amateur, Beautiful Girl, Big Tits, Blow, Creampie, FC2, POV, Uncensored",
    "actresses": "",
    "date": "2026-05-23",
    "page_url": "https://onejav.com/torrent/fc2ppv4903955"
  },
  {
    "code": "FC2PPV4904760",
    "title": "FC2-PPV-4904760 【個撮】一攫千金を狙い田舎暮らしを始めた家ゾㇰ。短絡的な旦那に振り回され、それでも身体を差し出し快楽に沈んでいく献身的な天然奥さん。どっちもどっちのフウフであった。",
    "size": "3.8 GB",
    "image_url": "https://contents-thumbnail2.fc2.com/w1280/storage201000.contents.fc2.com/file/350/34973626/1779357761.33.jpg",
    "torrent_url": "https://onejav.com/torrent/fc2ppv4904760/download/30989315/onejav.com_fc2ppv4904760.torrent",
    "tags": "Amateur, Black Hair, Breasts, FC2, Married Woman, Uncensored",
    "actresses": "",
    "date": "2026-05-23",
    "page_url": "https://onejav.com/torrent/fc2ppv4904760"
  },
  {
    "code": "FC2PPV4904818",
    "title": "FC2-PPV-4904818 【巨乳/個撮】魅惑の巨乳グラマラスボディ❣白肌Gカップの美人若妻さん♡乳輪ごと乳首を玩具責め♡チンポが埋まる肉感パイズリの後は生ハメ激ピストンで膣奥に大量中出しされちゃう迫力満点なハメ撮り映像♡",
    "size": "3.5 GB",
    "image_url": "https://contents-thumbnail2.fc2.com/w1280/storage201000.contents.fc2.com/file/400/39958499/1779361824.78.jpg",
    "torrent_url": "https://onejav.com/torrent/fc2ppv4904818/download/58260996/onejav.com_fc2ppv4904818.torrent",
    "tags": "Amateur, Beautiful Girl, Big Tits, Blow, Breasts, Creampie, FC2, Married Woman, POV",
    "actresses": "",
    "date": "2026-05-23",
    "page_url": "https://onejav.com/torrent/fc2ppv4904818"
  },
  {
    "code": "FC2PPV4904966",
    "title": "FC2-PPV-4904966 【個撮】初撮り☆最近まで処女だった！JDの18歳☆BODYを堪能♥手コキフェラもお上手♥ガチ興奮の中出し♥特典付き",
    "size": "3.5 GB",
    "image_url": "https://contents-thumbnail2.fc2.com/w1280/storage201000.contents.fc2.com/file/410/40984428/1779387194.23.jpg",
    "torrent_url": "https://onejav.com/torrent/fc2ppv4904966/download/50511371/onejav.com_fc2ppv4904966.torrent",
    "tags": "Amateur, Beautiful Girl, Creampie, FC2, POV, Uncensored",
    "actresses": "",
    "date": "2026-05-23",
    "page_url": "https://onejav.com/torrent/fc2ppv4904966"
  },
  {
    "code": "FC2PPV4904774",
    "title": "FC2-PPV-4904774 【6/12迄1290pt】【初撮】20歳CoCo〇番屋バイトリーダー。「あぁ、またイクゥ…！」巨根おじさんに沢山教育されてビクビク痙攣潮吹き。敏感なピンク色マンコにしっかり中出し。",
    "size": "4.1 GB",
    "image_url": "https://contents-thumbnail2.fc2.com/w1280/storage200000.contents.fc2.com/file/370/36940995/1779433817.57.png",
    "torrent_url": "https://onejav.com/torrent/fc2ppv4904774/download/51633701/onejav.com_fc2ppv4904774.torrent",
    "tags": "Amateur, Blow, Creampie, FC2, Squirting, Uncensored",
    "actresses": "",
    "date": "2026-05-23",
    "page_url": "https://onejav.com/torrent/fc2ppv4904774"
  },
  {
    "code": "FC2PPV4905339",
    "title": "FC2-PPV-4905339 【無修正】Eカップ!超S級美形ショートカット制服美女との放課後デート!敏感マンコで連続イキする早熟18歳に種付けピストン中出し交尾!!",
    "size": "2.3 GB",
    "image_url": "https://contents-thumbnail2.fc2.com/w1280/storage200000.contents.fc2.com/file/388/38722718/1779415227.27.jpg",
    "torrent_url": "https://onejav.com/torrent/fc2ppv4905339/download/13185747/onejav.com_fc2ppv4905339.torrent",
    "tags": "Amateur, Blow, Creampie, FC2, POV, Uncensored",
    "actresses": "",
    "date": "2026-05-23",
    "page_url": "https://onejav.com/torrent/fc2ppv4905339"
  },
  {
    "code": "FC2PPV4904563",
    "title": "FC2-PPV-4904563 無修正.界隈でプチバズりする前のFカップ神乳素人J⚫︎との※性行為ハメ撮り映像です【本性】他の人とは絶対にハメ撮りなんてしないからね…?嘘を付かれたので濃厚クリーミーな中出し2連発と同時に初撮影動画を",
    "size": "4.4 GB",
    "image_url": "https://contents-thumbnail2.fc2.com/w1280/storage201000.contents.fc2.com/file/407/40600830/1779433777.89.png",
    "torrent_url": "https://onejav.com/torrent/fc2ppv4904563/download/74166284/onejav.com_fc2ppv4904563.torrent",
    "tags": "Amateur, Big Tits, Breasts, Creampie, FC2, Uncensored",
    "actresses": "",
    "date": "2026-05-23",
    "page_url": "https://onejav.com/torrent/fc2ppv4904563"
  },
  {
    "code": "FC2PPV4904990",
    "title": "FC2-PPV-4904990 【完全素人&amp;初撮り】可愛くて恥ずかしがり屋の初々しい19歳！押しに弱く流れのまま人生初中出しハメ♡特典有り",
    "size": "6.9 GB",
    "image_url": "https://contents-thumbnail2.fc2.com/w1280/storage200000.contents.fc2.com/file/392/39151056/1779397282.11.jpg",
    "torrent_url": "https://onejav.com/torrent/fc2ppv4904990/download/19237597/onejav.com_fc2ppv4904990.torrent",
    "tags": "Amateur, Back, Beautiful Girl, Blow, Creampie, Debut Production, FC2, POV",
    "actresses": "",
    "date": "2026-05-23",
    "page_url": "https://onejav.com/torrent/fc2ppv4904990"
  }
]