[
  {
    "code": "ARSO26206",
    "title": "舞ワイフ ～セレブ倶楽部～ 206",
    "size": "8.7 GB",
    "image_url": "https://pics.dmm.co.jp/mono/movie/adult/1arso26206/1arso26206pl.jpg",
    "torrent_url": "https://onejav.com/torrent/arso26206/download/73326036/onejav.com_arso26206.torrent",
    "tags": "Affair, Breasts, Creampie, Married Woman, Mature Woman, Slender",
    "actresses": "",
    "date": "2026-05-21",
    "page_url": "https://onejav.com/torrent/arso26206"
  },
  {
    "code": "200GANA3384",
    "title": "エステティシャンの色気、反則。今日の相手の熱量にこっちも持ってかれて、人生トップクラスに盛り上がった。彼女の溜まった性欲のはけ口になれて、よかったwww マジ軟派、初撮。 2298",
    "size": "2.9 GB",
    "image_url": "https://image.mgstage.com/images/nanpatv/200gana/3384/pb_e_200gana-3384.jpg",
    "torrent_url": "https://onejav.com/torrent/200gana3384/download/42512260/onejav.com_200gana3384.torrent",
    "tags": "Amateur, Cum, Nampa, Older Sister",
    "actresses": "",
    "date": "2026-05-21",
    "page_url": "https://onejav.com/torrent/200gana3384"
  },
  {
    "code": "420STH127",
    "title": "KATAOKA(20)【素人ホイホイStayHome/自宅連れ込み/素人/美少女/清楚/顔射/ハメ撮り/ドキュメンタリー】",
    "size": "2.7 GB",
    "image_url": "https://image.mgstage.com/images/hoihoiz/420sth/127/pb_e_420sth-127.jpg",
    "torrent_url": "https://onejav.com/torrent/420sth127/download/29271626/onejav.com_420sth127.torrent",
    "tags": "Amateur, Beautiful Girl, Facials, POV",
    "actresses": "",
    "date": "2026-05-21",
    "page_url": "https://onejav.com/torrent/420sth127"
  },
  {
    "code": "483TMG002",
    "title": "",
    "size": "3.5 GB",
    "image_url": "https://image.mgstage.com/images/hamechan/483tmg/002/pb_e_483tmg-002.jpg",
    "torrent_url": "https://onejav.com/torrent/483tmg002/download/69961887/onejav.com_483tmg002.torrent",
    "tags": "",
    "actresses": "",
    "date": "2026-05-21",
    "page_url": "https://onejav.com/torrent/483tmg002"
  },
  {
    "code": "892OERO001",
    "title": "結婚して一年の新婚妻…なのに他の男と会ってんの？「刺激とトキメキが足りなくて…」って言いながら、エロがってくる欲求不満な人妻を好き放題ヤリまくり。最初「生はダメ」って言ってたのに、ま◯こをクパァと広げて「ここに精子欲しいです」って…そんなんエロ過ぎて、逝。",
    "size": "2.4 GB",
    "image_url": "https://image.mgstage.com/images/kyantamaseisouin/892oero/001/pb_e_892oero-001.jpg",
    "torrent_url": "https://onejav.com/torrent/892oero001/download/23512558/onejav.com_892oero001.torrent",
    "tags": "Affair, Amateur, Big Tits, Creampie, Married Woman, POV",
    "actresses": "",
    "date": "2026-05-21",
    "page_url": "https://onejav.com/torrent/892oero001"
  },
  {
    "code": "SIRO5667",
    "title": "148cmミニマム女子の窮屈マ●コをドチュドチュ重圧ピストンで掘削！！潮ふきちらしのドロドロマ●コで快楽に撃沈！理性が保てない！！ 【初撮り】ネットでAV応募→AV体験撮影 2559",
    "size": "2.4 GB",
    "image_url": "https://image.mgstage.com/images/shirouto/siro/5667/pb_e_siro-5667.jpg",
    "torrent_url": "https://onejav.com/torrent/siro5667/download/17565528/onejav.com_siro5667.torrent",
    "tags": "Amateur, Beautiful legs, Butt, Debut Production, Instructor, POV, Shaved",
    "actresses": "",
    "date": "2026-05-21",
    "page_url": "https://onejav.com/torrent/siro5667"
  },
  {
    "code": "JURA194",
    "title": "初撮り人妻ドキュメント第二章 工藤香澄",
    "size": "4.9 GB",
    "image_url": "https://pics.dmm.co.jp/mono/movie/adult/h_086jura194/h_086jura194pl.jpg",
    "torrent_url": "https://onejav.com/torrent/jura194/download/37366910/onejav.com_jura194.torrent",
    "tags": "3P, 4P, Big Tits, Documentary, Married Woman, Mature Woman, Solowork",
    "actresses": "工藤香澄",
    "date": "2026-05-21",
    "page_url": "https://onejav.com/torrent/jura194"
  },
  {
    "code": "JURA195",
    "title": "初撮り五十路妻ドキュメント第二章 牧瀬すみの",
    "size": "5.2 GB",
    "image_url": "https://pics.dmm.co.jp/mono/movie/adult/h_086jura195/h_086jura195pl.jpg",
    "torrent_url": "https://onejav.com/torrent/jura195/download/84386033/onejav.com_jura195.torrent",
    "tags": "3P, 4P, Big Tits, Documentary, Married Woman, Mature Woman, Solowork",
    "actresses": "牧瀬すみの",
    "date": "2026-05-21",
    "page_url": "https://onejav.com/torrent/jura195"
  },
  {
    "code": "MEKO396",
    "title": "マッチングアプリナンパ中出し不倫SEX019",
    "size": "5.7 GB",
    "image_url": "https://pics.dmm.co.jp/mono/movie/adult/h_1160meko396/h_1160meko396pl.jpg",
    "torrent_url": "https://onejav.com/torrent/meko396/download/88890866/onejav.com_meko396.torrent",
    "tags": "Amateur, Married Woman, Mature Woman, Nampa, POV",
    "actresses": "",
    "date": "2026-05-21",
    "page_url": "https://onejav.com/torrent/meko396"
  },
  {
    "code": "MESU142",
    "title": "三ツ星熟女ソープ 入店初日の泡姫と射精無制限で過ごすラッキーなひととき 青葉小夏",
    "size": "4.7 GB",
    "image_url": "https://pics.dmm.co.jp/mono/movie/adult/h_086mesu142/h_086mesu142pl.jpg",
    "torrent_url": "https://onejav.com/torrent/mesu142/download/98340642/onejav.com_mesu142.torrent",
    "tags": "Creampie, Lingerie, Married Woman, Mature Woman, Soapland, Solowork",
    "actresses": "青葉小夏",
    "date": "2026-05-21",
    "page_url": "https://onejav.com/torrent/mesu142"
  }
]